PyConSolv/ConfGen.py
PyConSolv/__init__.py
PyConSolv/pyconsolv.py
PyConSolv/counterions/BARF.frcmod
PyConSolv/counterions/BARF.mol2
PyConSolv/counterions/BF4.frcmod
PyConSolv/counterions/BF4.mol2
PyConSolv/counterions/BPH.frcmod
PyConSolv/counterions/BPH.mol2
PyConSolv/counterions/CLO.frcmod
PyConSolv/counterions/CLO.mol2
PyConSolv/counterions/OTF.frcmod
PyConSolv/counterions/OTF.mol2
PyConSolv/counterions/PF6.frcmod
PyConSolv/counterions/PF6.mol2
PyConSolv/counterions/SCF.frcmod
PyConSolv/counterions/SCF.mol2
PyConSolv/db/atom-radius.txt
PyConSolv/db/metal-radius.txt
PyConSolv/interfaces/__init__.py
PyConSolv/interfaces/amber.py
PyConSolv/interfaces/calculate.py
PyConSolv/interfaces/cpptraj.py
PyConSolv/interfaces/gromacs.py
PyConSolv/interfaces/mdengines.py
PyConSolv/interfaces/multiWFN.py
PyConSolv/interfaces/parmed.py
PyConSolv/misc/__init__.py
PyConSolv/misc/analysis.py
PyConSolv/misc/clustering.py
PyConSolv/misc/converter.py
PyConSolv/misc/coordinateCheck.py
PyConSolv/misc/counterion.py
PyConSolv/misc/counterionGen.py
PyConSolv/misc/files.py
PyConSolv/misc/filestructure.py
PyConSolv/misc/frcmod.py
PyConSolv/misc/inputparser.py
PyConSolv/misc/ions.py
PyConSolv/misc/mol2.py
PyConSolv/misc/outgen.py
PyConSolv/misc/parameterChecker.py
PyConSolv/misc/parametrizerInterface.py
PyConSolv/misc/pathchecker.py
PyConSolv/misc/restart.py
PyConSolv/misc/solvenGen.py
PyConSolv/misc/solvent.py
PyConSolv/misc/tleapAdderInterface.py
PyConSolv/misc/ui.py
PyConSolv/scripts_and_inputs/align.in
PyConSolv/scripts_and_inputs/align_dry.in
PyConSolv/scripts_and_inputs/cluster_kmeans.in
PyConSolv/scripts_and_inputs/dry.vmd
PyConSolv/scripts_and_inputs/dry_aligned.vmd
PyConSolv/scripts_and_inputs/dry_sim.in
PyConSolv/scripts_and_inputs/run_simulation.sh
PyConSolv/scripts_and_inputs/run_simulation_gro.sh
PyConSolv/scripts_and_inputs/simulation.in
PyConSolv/scripts_and_inputs/simulation_cart.in
PyConSolv/scripts_and_inputs/simulation_gro.mdp
pyconsolv-1.0.6.3.1.dist-info/METADATA
pyconsolv-1.0.6.3.1.dist-info/WHEEL
pyconsolv-1.0.6.3.1.dist-info/entry_points.txt
pyconsolv-1.0.6.3.1.dist-info/licenses/LICENSE
pyconsolv-1.0.6.3.1.dist-info/RECORD
