Metadata-Version: 2.3
Name: PyConSolv
Version: 1.0.6.3.1
Summary: A package for conformer generation of transition-metal-containing complexes
Project-URL: Homepage, https://github.com/PodewitzLab/PyConSolv
Project-URL: Bug Tracker, https://github.com/PodewitzLab/PyConSolv/issues
Author-email: "R. A. Talmazan" <radu.talmazan@tuwien.ac.at>
License-File: LICENSE
Keywords: AmberTools,Conformer,Explicit Solvent,Generator,MCPB,ORCA,Parametrization,PyConSolv,Simulation,Solvation,Transition metals
Classifier: Intended Audience :: Science/Research
Classifier: License :: OSI Approved :: GNU General Public License v3 (GPLv3)
Classifier: Natural Language :: English
Classifier: Operating System :: Unix
Classifier: Programming Language :: Python :: 3
Classifier: Topic :: Scientific/Engineering :: Chemistry
Requires-Python: >=3.10
Requires-Dist: matplotlib>=3.5.3
Requires-Dist: numpy>=1.23.1
Requires-Dist: pandas>=1.4.3
Requires-Dist: parmed>=4.2.0
Requires-Dist: rdkit>=2022.09.1
